[{"label": "None", "value": 1}, {"label": "Blue Laser Sword", "value": 2}, {"label": "Charge Rifle", "value": 3}, {"label": "Demon Blades", "value": 4}, {"label": "Devil Blade", "value": 5}, {"label": "Double Devil Blade", "value": 6}, {"label": "Double Sword", "value": 7}, {"label": "Dragon Claws", "value": 8}, {"label": "Flower", "value": 9}, {"label": "Frozen Wand", "value": 10}, {"label": "Frying Pan", "value": 11}, {"label": "Golden Laser Whip", "value": 12}, {"label": "Golden Nunchucks", "value": 13}, {"label": "Green Laser Sword", "value": 14}, {"label": "Hockey Stick", "value": 15}, {"label": "Nunchucks", "value": 16}, {"label": "Pink Destiny Sword", "value": 17}, {"label": "Saber", "value": 18}, {"label": "Sais", "value": 19}, {"label": "Snake Whip", "value": 20}, {"label": "Space Blaster", "value": 21}, {"label": "Stripper Pole", "value": 22}, {"label": "Taser", "value": 23}, {"label": "White Laser Whip", "value": 24}]