[
  {
    "Alien Species": {
      "Avatar": 580,
      "Bug": 144,
      "Furry": 629,
      "Ghost": 610,
      "Ginger": 418,
      "Grey": 501,
      "Hologram": 143,
      "Joker": 207,
      "Monarch": 332,
      "Najdorf": 183,
      "Nordic": 650,
      "Pinky": 258,
      "Python": 509,
      "Reptilian": 495,
      "Robot": 273,
      "Shadow": 389,
      "Tang": 345
    },
    "Outfit": {
      "Bikini": 193,
      "Blue Body Suit": 553,
      "Bubbles": 176,
      "Censored": 165,
      "Crop Top": 321,
      "Green Mini Skirt": 279,
      "Green T-Shirt": 442,
      "Latex": 419,
      "Nude": 60,
      "Orange Bulls Eye": 489,
      "Pink T-Shirt": 500,
      "Red Bulls Eye": 409,
      "Red Mini Skirt": 241,
      "Romper": 590,
      "Space Suit": 672,
      "Swimsuit": 333,
      "Topless": 213,
      "Yellow Body Suit": 598,
      "T-Shirt": 13
    },
    "Accessories": {
      "None": 711,
      "Eyelite": 618,
      "Pink Bubblegum": 370,
      "Nerd Glasses": 583,
      "Orange Shades": 538,
      "Cybernetic Implant": 490,
      "Cyclops": 476,
      "Green Visor": 489,
      "Pink Visor": 393,
      "Cyber Goggles": 383,
      "Pink Cyber Goggles": 371,
      "Green Heart Glasses": 281,
      "Red Heart Glasses": 301,
      "Red Bubblegum": 208,
      "Purple Bubblegum": 162,
      "Neon Green Triangle Glasses": 135,
      "Neon Pink Triangle Glasses": 96,
      "Scouter": 61
    },
    "Earrings": {
      "None": 674,
      "Blue Laser": 0,
      "Cross": 538,
      "Diamond": 363,
      "Digital": 171,
      "Double Line": 103,
      "Emerald": 373,
      "Geometric": 286,
      "Green Heart": 437,
      "Green Hoop": 604,
      "Microchip": 134,
      "Orange Hoop": 521,
      "Pink Hoop": 690,
      "Red Heart": 458,
      "Red Laser": 0,
      "Ruby": 451,
      "Sapphire": 529,
      "Triangle": 334
    },
    "Vortex": {
      "Green": 933,
      "Orange": 1357,
      "Pink": 480,
      "Purple": 274,
      "Red": 1472,
      "Teal": 147,
      "White": 705,
      "Yellow": 1298
    }
  },
  {
    "Gloves": {
      "None": 651,
      "Blue Cybernetic": 189,
      "Blue Neon Bracelet": 345,
      "Brass Knuckles": 449,
      "Checkered": 575,
      "Diamond Bracelet": 158,
      "Fishnet": 569,
      "Gold Bracelet": 140,
      "Green Laser Bracer": 104,
      "Latex": 461,
      "Orange Neon Bracelet": 347,
      "Pink Cybernetic": 222,
      "Pink Laser Bracer": 91,
      "Pink Neon Bracelet": 419,
      "Power Gloves": 421,
      "Red Laser Bracer": 64,
      "Space Gloves": 654,
      "Spiked": 525,
      "White Neon Bracer": 282
    },
    "Shoes": {
      "Barefoot": 598,
      "Blue Cybernetic": 262,
      "Checkered Boots": 554,
      "Chunky Pumps": 539,
      "Green Hoverboard": 108,
      "High Heels": 329,
      "Latex Boots": 445,
      "Mary Janes": 447,
      "Mesh Pumps": 510,
      "Pink Cybernetic": 178,
      "Pink Hoverboard": 87,
      "Pleasers": 225,
      "Roller Skates": 172,
      "Rollerblades": 132,
      "Ruby Slippers": 97,
      "Sneakers": 626,
      "Space Boots": 598,
      "Spiked Garters": 350,
      "Thigh Highs": 409
    },
    "Hair": {
      "Bangs": 407,
      "Bowl Cut": 230,
      "Braids": 299,
      "Buzzcut": 399,
      "Cleopatra": 173,
      "Curl": 447,
      "Curly": 361,
      "Dorothy": 149,
      "Fro": 255,
      "Leia": 144,
      "Marilyn": 148,
      "Mohawk": 241,
      "Mullet": 197,
      "Pigtails": 218,
      "Pixie": 389,
      "Ponytail": 469,
      "Rat Tail": 203,
      "Shaggy": 426,
      "Shaved": 223,
      "Slick": 273,
      "Spiked": 240,
      "Teased": 268,
      "Twist": 210,
      "Wavy": 297
    },
    "Boobs": {
      "A": 1406,
      "B": 1301,
      "C": 1062,
      "D": 1005,
      "E": 882,
      "F": 738,
      "G": 272
    },
    "Stars": {
      "Blue": 1532,
      "Green": 1396,
      "Multicolored": 659,
      "Orange": 1259,
      "Purple": 805,
      "Red": 279,
      "Teal": 736
    },
    "Hairspray": {
      "Yes": 2052,
      "No": 4614
    }
  },
  {
    "Accent Colors": {
      "Aqua": 219,
      "Black": 488,
      "Blue": 253,
      "Brown": 421,
      "Bronze": 423,
      "Copper": 400,
      "Crimson": 269,
      "Dark Red": 287,
      "Golden": 317,
      "Green": 223,
      "Lime": 205,
      "Magenta": 178,
      "Maroon": 254,
      "Navy": 243,
      "Orange": 355,
      "Orchid": 156,
      "Pink": 154,
      "Purple": 208,
      "Red": 288,
      "Silver": 143,
      "Spring Green": 208,
      "Turquoise": 254,
      "Wheat": 366,
      "Yellow": 354
    },
    "Power": {
      "None": 5495,
      "Boob": 272,
      "Cleopatra": 11,
      "Dorothy": 47,
      "Heart": 116,
      "Latex": 59,
      "Leia": 29,
      "Marilyn": 9,
      "Pussy": 7,
      "Space": 38,
      "Spiked": 60,
      "Style": 581
    },
    "Weapons": {
      "None": 388,
      "Blue Laser Sword": 287,
      "Charge Rifle": 271,
      "Demon Blades": 205,
      "Devil Blade": 228,
      "Double Devil Blade": 163,
      "Double Sword": 202,
      "Dragon Claws": 178,
      "Flower": 410,
      "Frozen Wand": 302,
      "Frying Pan": 400,
      "Golden Laser Whip": 224,
      "Golden Nunchucks": 133,
      "Green Laser Sword": 205,
      "Hockey Stick": 360,
      "Nunchucks": 261,
      "Pink Destiny Sword": 160,
      "Saber": 400,
      "Sais": 336,
      "Snake Whip": 242,
      "Space Blaster": 451,
      "Stripper Pole": 365,
      "Taser": 232,
      "White Laser Whip": 263
    },
    "Necklace": {
      "None": 606,
      "Blood Vial": 108,
      "Blue Neon": 461,
      "Bullet": 122,
      "Chain": 557,
      "Choker": 590,
      "Cybernetic Implant": 168,
      "Dog Tags": 637,
      "Green Neon": 443,
      "Heart Choker": 475,
      "Laser": 295,
      "Lock": 193,
      "Orange Neon": 356,
      "Pink Laser": 332,
      "Pink Neon": 402,
      "Reflective": 266,
      "Spiked": 576,
      "Vampire": 79
    },
    "Helmets": {
      "No": 4651,
      "Yes": 2015
    }
  }
]
