[
  {
    "Alien Species": {
      "Common": [
        { "label": "Nordic", "percentage": 10.17 },
        { "label": "Ghost", "percentage": 8.99 },
        { "label": "Furry", "percentage": 8.08 }
      ],
      "Uncommon": [
        { "label": "Avatar", "percentage": 8.08 },
        { "label": "Grey", "percentage": 7.29 },
        { "label": "Python", "percentage": 6.93 }
      ],
      "Rare": [
        { "label": "Ginger", "percentage": 6.86 },
        { "label": "Reptilian", "percentage": 6.83 }
      ],
      "Epic": [
        { "label": "Tang", "percentage": 6.47 },
        { "label": "Monarch", "percentage": 6.45 }
      ],
      "Legendary": [
        { "label": "Robot", "percentage": 6.25 },
        { "label": "Pinky", "percentage": 5.13 }
      ],
      "Unicorn": [
        { "label": "Najdorf", "percentage": 3.92 },
        { "label": "Joker", "percentage": 3.88 }
      ],
      "Holygrail": [
        { "label": "Bug", "percentage": 2.75 },
        { "label": "Hologram", "percentage": 1.91 }
      ]
    },
    "Outfit": {
      "Common": [{ "label": "Space Suit", "percentage": 21.38 }],
      "Uncommon": [
        { "label": "Romper", "percentage": 12.87 },
        { "label": "Body Suit", "percentage": 12.42 }
      ],
      "Rare": [
        { "label": "T-Shirt", "percentage": 10.14 },
        { "label": "Latex", "percentage": 8.92 }
      ],
      "Epic": [
        { "label": "Crop Top", "percentage": 8.55 },
        { "label": "Mini Skirt", "percentage": 7.81 }
      ],
      "Legendary": [{ "label": "Bikini", "percentage": 7.0 }],
      "Unicorn": [{ "label": "Topless", "percentage": 6.12 }],
      "Holygrail": [{ "label": "Nude", "percentage": 4.78 }]
    },
    "Boob Size": {
      "Common": [{ "label": "A", "percentage": 23.4 }],
      "Uncommon": [{ "label": "B", "percentage": 20.85 }],
      "Rare": [{ "label": "C", "percentage": 18.91 }],
      "Epic": [{ "label": "D", "percentage": 12.72 }],
      "Legendary": [{ "label": "E", "percentage": 11.0 }],
      "Unicorn": [{ "label": "F", "percentage": 9.19 }],
      "Holygrail": [{ "label": "G", "percentage": 4 }]
    },
    "Hair": {
      "Common": [
        { "label": "Ponytail", "percentage": 9.12 },
        { "label": "Buzzcut", "percentage": 8.27 },
        { "label": "Shaggy", "percentage": 6.57 },
        { "label": "Curl", "percentage": 5.99 }
      ],
      "Uncommon": [
        { "label": "Bangs", "percentage": 5.28 },
        { "label": "Spiked", "percentage": 5.15 },
        { "label": "Curly", "percentage": 5.02 },
        { "label": "Pixie", "percentage": 4.94 }
      ],
      "Rare": [
        { "label": "Wavy", "percentage": 4.77 },
        { "label": "Braids", "percentage": 4.22 },
        { "label": "Bowl Cut", "percentage": 4.19 },
        { "label": "Slick", "percentage": 3.96 }
      ],
      "Epic": [
        { "label": "Teased", "percentage": 3.91 },
        { "label": "Fro", "percentage": 3.85 },
        { "label": "Rat Tail", "percentage": 3.15 },
        { "label": "Mullet", "percentage": 2.99 }
      ],
      "Legendary": [
        { "label": "Pigtails", "percentage": 2.94 },
        { "label": "Shaved", "percentage": 2.84 },
        { "label": "Mohawk", "percentage": 2.77 },
        { "label": "Twist", "percentage": 2.75 }
      ],
      "Unicorn": [
        { "label": "Leia", "percentage": 2.17 },
        { "label": "Marilyn", "percentage": 2.04 }
      ],
      "Holygrail": [
        { "label": "Cleopatra", "percentage": 1.76 },
        { "label": "Dorothy", "percentage": 1.34 }
      ]
    },
    "Hairspray Bonus": {
      "0": [
        { "label": "No", "percentage": 76.96 },
        { "label": "Yes", "percentage": 23.03 }
      ]
    }
  },
  {
    "Accent Color": {
      "Common": [
        { "label": "Black", "percentage": 9.23 },
        { "label": "Brown", "percentage": 8.04 },
        { "label": "Bronze", "percentage": 6.43 },
        { "label": "Copper", "percentage": 6.23 }
      ],
      "Uncommon": [
        { "label": "Red", "percentage": 5.49 },
        { "label": "Yellow", "percentage": 5.25 },
        { "label": "Orange", "percentage": 5.04 },
        { "label": "Wheat", "percentage": 4.87 }
      ],
      "Rare": [
        { "label": "Golden", "percentage": 4.69 },
        { "label": "Crimson", "percentage": 4.21 },
        { "label": "Dark Red", "percentage": 4.07 },
        { "label": "Blue", "percentage": 3.99 }
      ],
      "Epic": [
        { "label": "Turqoise", "percentage": 3.9 },
        { "label": "Maroon", "percentage": 3.95 },
        { "label": "Spring Green", "percentage": 3.1 },
        { "label": "Green", "percentage": 2.95 }
      ],
      "Legendary": [
        { "label": "Aqua", "percentage": 2.94 },
        { "label": "Navy", "percentage": 2.94 },
        { "label": "Purple", "percentage": 2.93 },
        { "label": "Lime", "percentage": 2.88 }
      ],
      "Unicorn": [
        { "label": "Magenta", "percentage": 2.01 },
        { "label": "Pink", "percentage": 2.0 },
        { "label": "Orchid", "percentage": 1.9 }
      ],
      "Holygrail": [{ "label": "Silver", "percentage": 0.9 }]
    },
    "Shoes": {
      "Common": [{ "label": "Space Boots", "percentage": 12.66 }],
      "Uncommon": [
        { "label": "Barefoot", "percentage": 10.57 },
        { "label": "Sneakers", "percentage": 8.72 }
      ],
      "Rare": [
        { "label": "Chunky Pumps", "percentage": 7.84 },
        { "label": "Mesh Pumps", "percentage": 7.83 }
      ],
      "Epic": [
        { "label": "Mary Janes", "percentage": 7.53 },
        { "label": "Thigh Highs", "percentage": 6.9 },
        { "label": "Latex Boots", "percentage": 6.55 }
      ],
      "Legendary": [
        { "label": "Spiked Thigh Highs", "percentage": 6.02 },
        { "label": "High Heels", "percentage": 5.81 },
        { "label": "Cybernetic", "percentage": 5.13 }
      ],
      "Unicorn": [
        { "label": "Roller Skates", "percentage": 4.94 },
        { "label": "Rollerblades", "percentage": 3.95 },
        { "label": "Hoverboard", "percentage": 3.22 }
      ],
      "Holygrail": [{ "label": "Ruby Slippers", "percentage": 2.22 }]
    },
    "Accessories": {
      "Common": [{ "label": "None", "percentage": 26.53 }],
      "Uncommon": [
        { "label": "Eyelite", "percentage": 18.27 },
        { "label": "Blue Shades", "percentage": 13.71 }
      ],
      "Rare": [{ "label": "Cyclops", "percentage": 10.91 }],
      "Epic": [{ "label": "Visor", "percentage": 10.58 }],
      "Legendary": [{ "label": "Cyber Goggles", "percentage": 8.77 }],
      "Unicorn": [{ "label": "Heart Glasses", "percentage": 7.16 }],
      "Holygrail": [{ "label": "Neon Triangle Glasses", "percentage": 4.06 }]
    },
    "Gloves": {
      "Common": [{ "label": "Space Gloves", "percentage": 25.75 }],
      "Uncommon": [{ "label": "None", "percentage": 19.07 }],
      "Rare": [
        { "label": "Fishnet", "percentage": 13.32 },
        { "label": "Latex", "percentage": 11.18 }
      ],
      "Epic": [{ "label": "Spiked", "percentage": 10.62 }],
      "Legendary": [{ "label": "Brass Knuckles", "percentage": 8.97 }],
      "Unicorn": [{ "label": "Cybernetic", "percentage": 7.09 }],
      "Holygrail": [{ "label": "Power Gloves", "percentage": 3.99 }]
    },
    "Helmet": {
      "0": [
        { "label": "No", "percentage": 77.47 },
        { "label": "Yes", "percentage": 22.52 }
      ]
    },
    "Signature": {
      "0": [
        { "label": "No", "percentage": 97.99 },
        { "label": "Yes", "percentage": 2.0 }
      ]
    }
  },
  {
    "Necklace": {
      "Common": [{ "label": "None", "percentage": 22.63 }],
      "Uncommon": [
        { "label": "Dog Tags", "percentage": 19.31 },
        { "label": "Spiked", "percentage": 12.71 }
      ],
      "Rare": [{ "label": "Chain", "percentage": 11.1 }],
      "Epic": [{ "label": "Heart Choker", "percentage": 9.74 }],
      "Legendary": [
        { "label": "Blue Neon", "percentage": 7.96 },
        { "label": "Green Neon", "percentage": 5.87 }
      ],
      "Unicorn": [
        { "label": "Pink Neon", "percentage": 4.7 },
        { "label": "Reflective", "percentage": 4.25 }
      ],
      "Holygrail": [{ "label": "Laser", "percentage": 1.72 }]
    },
    "Weapon": {
      "Common": [{ "label": "Space Blaster", "percentage": 23.18 }],
      "Uncommon": [
        { "label": "None", "percentage": 9.15 },
        { "label": "Stripper Pole", "percentage": 9.11 },
        { "label": "Frying Pan", "percentage": 6.94 }
      ],
      "Rare": [
        { "label": "Flower", "percentage": 5.91 },
        { "label": "Sais", "percentage": 5.13 },
        { "label": "Nunchucks", "percentage": 5.11 }
      ],
      "Epic": [
        { "label": "Blue Laser Sword", "percentage": 4.68 },
        { "label": "Frozen Wnd", "percentage": 4.04 },
        { "label": "Snake Whip", "percentage": 3.95 }
      ],
      "Legendary": [
        { "label": "Charge Rifle", "percentage": 3.73 },
        { "label": "Laser Whip", "percentage": 3.22 },
        { "label": "Dragon Claws", "percentage": 3.05 }
      ],
      "Unicorn": [
        { "label": "Taser", "percentage": 2.87 },
        { "label": "Green Laser Sword", "percentage": 2.8 },
        { "label": "Double Sword", "percentage": 2.71 }
      ],
      "Holygrail": [
        { "label": "Devil Blade", "percentage": 2.41 },
        { "label": "Pink Destiny Sword", "percentage": 2.0 }
      ]
    },
    "Power": {
      "Common": [{ "label": "None", "percentage": 67.51 }],
      "Uncommon": [{ "label": "Style", "percentage": 24.32 }],
      "Rare": [{ "label": "Boob", "percentage": 3.92 }],
      "Epic": [
        { "label": "Latex", "percentage": 2.3 },
        { "label": "Spiked", "percentage": 2.16 }
      ],
      "Legendary": [
        { "label": "Heart", "percentage": 1.45 },
        { "label": "Pussy", "percentage": 1.26 }
      ],
      "Unicorn": [
        { "label": "Space", "percentage": 0.42 },
        { "label": "Dorothy", "percentage": 0.39 },
        { "label": "Leia", "percentage": 0.25 }
      ],
      "Holygrail": [{ "label": "Cleopatra", "percentage": 0.03 }]
    },
    "Stars": {
      "Common": [{ "label": "Blue", "percentage": 22.58 }],
      "Uncommon": [{ "label": "Green", "percentage": 21.27 }],
      "Rare": [{ "label": "Orange", "percentage": 18.96 }],
      "Epic": [{ "label": "Purple", "percentage": 13.19 }],
      "Legendary": [{ "label": "Teal", "percentage": 10.8 }],
      "Unicorn": [{ "label": "Multicolored", "percentage": 9.05 }],
      "Holygrail": [{ "label": "Red", "percentage": 4.14 }]
    },
    "Earrings": {
      "Common": [{ "label": "None", "percentage": 25.83 }],
      "Uncommon": [
        { "label": "Hoop", "percentage": 18.92 },
        { "label": "Cross", "percentage": 13.52 }
      ],
      "Rare": [{ "label": "Heart", "percentage": 11.14 }],
      "Epic": [{ "label": "Sapphire", "percentage": 10.64 }],
      "Legendary": [{ "label": "Ruby", "percentage": 8.99 }],
      "Unicorn": [{ "label": "Emerald", "percentage": 6.96 }],
      "Holygrail": [{ "label": "Diamond", "percentage": 3.99 }]
    }
  }
]
